mzapi/__init__.py
mzapi/baidu/__init__.py
mzapi/baidu/authorization.py
mzapi/baidu/nlp/__init__.py
mzapi/tencent/__init__.py
mzapi/tencent/ocr/GeneralBasicOCR.py
mzapi/tencent/ocr/__init__.py
mzapi/utlis/__init__.py
mzapi/utlis/tencent_auth.py
mzapi_python-0.0.7.dist-info/licenses/LICENSE
mzapi_python-0.0.7.dist-info/METADATA
mzapi_python-0.0.7.dist-info/WHEEL
mzapi_python-0.0.7.dist-info/top_level.txt
mzapi_python-0.0.7.dist-info/RECORD
