Metadata-Version: 2.4
Name: mzapi-python
Version: 0.0.7
Summary: MZAPI的python的SDK
Home-page: https://github.com/xiaomizhoubaobei/MZAPI-Python
Author: 祁潇潇
Author-email: qixiaoxin@stu.sqxy.edu.cn
Project-URL: Bug Reports, https://github.com/xiaomizhoubaobei/MZAPI-Python/issues
Project-URL: Source, https://github.com/xiaomizhoubaobei/MZAPI-Python
Project-URL: Homepage, https://pypi.org/project/mzapi-python
Project-URL: Download, https://pypi.org/project/mzapi-python/#files
Project-URL: Changelog, https://github.com/xiaomizhoubaobei/MZAPI-Python/CHANGELOG.md
Project-URL: Documentation, https://docs.mizhoubaobei.top
Project-URL: GitHub, https://github.com/xiaomizhoubaobei/MZAPI-Python
Keywords: API SDK MZAPI PYTHON
Classifier: Development Status :: 3 - Alpha
Classifier: Intended Audience :: Developers
Classifier: License :: OSI Approved :: MIT License
Classifier: Operating System :: OS Independent
Classifier: Programming Language :: Python :: 3
Classifier: Programming Language :: Python :: 3.10
Classifier: Programming Language :: Python :: 3.11
Classifier: Programming Language :: Python :: 3.12
Classifier: Programming Language :: Python :: 3.13
Requires-Python: >=3.7
License-File: LICENSE
Requires-Dist: requests
Requires-Dist: pytz
Provides-Extra: dev
Requires-Dist: pytest>=6.0; extra == "dev"
Requires-Dist: pytest-cov>=2.0; extra == "dev"
Requires-Dist: black>=21.0; extra == "dev"
Requires-Dist: flake8>=3.8; extra == "dev"
Dynamic: author
Dynamic: author-email
Dynamic: classifier
Dynamic: description
Dynamic: description-content-type
Dynamic: home-page
Dynamic: keywords
Dynamic: license-file
Dynamic: project-url
Dynamic: provides-extra
Dynamic: requires-dist
Dynamic: requires-python
Dynamic: summary
